{
  "$schema": "https://json.schemastore.org/tsconfig",
  "compilerOptions": {
    "esModuleInterop": true,
    "incremental": false,
    "isolatedModules": true,
    "lib": ["ES2022"],
    "module": "ESNext",
    "moduleDetection": "force",
    "moduleResolution": "bundler",
    "noEmit": true,
    "noUncheckedIndexedAccess": true,
    "resolveJsonModule": true,
    "skipLibCheck": true,
    "strict": true,
    "target": "ES2022",
    "noFallthroughCasesInSwitch": true,
    "noImplicitReturns": true,
    "noImplicitOverride": true,
    "noUncheckedSideEffectImports": true,
    "noUnusedLocals": true,
    "noUnusedParameters": true,
    "allowUnusedLabels": false,
    "allowUnreachableCode": false
  }
}
